aiai/__init__.py
aiai-0.0.1.dist-info/LICENSE
aiai-0.0.1.dist-info/WHEEL
aiai-0.0.1.dist-info/METADATA
aiai-0.0.1.dist-info/RECORD
