Metadata-Version: 2.1
Name: aiai
Version: 0.0.1
Summary: Alexandra Institute Artificial Intelligence, a Python package for Danish data science.
License: MIT
Author: Dan Saattrup Nielsen
Author-email: dan.nielsen@alexandra.dk
Requires-Python: >=3.8,<3.11
Classifier: License :: OSI Approved :: MIT License
Classifier: Programming Language :: Python :: 3
Classifier: Programming Language :: Python :: 3.10
Classifier: Programming Language :: Python :: 3.8
Classifier: Programming Language :: Python :: 3.9
Requires-Dist: aiai_eval (>=0.0.1,<0.0.2)
